MANIFEST.in
changelog.txt
licence.txt
readme.txt
setup.py
taicalculator/__init__.py
taicalculator.egg-info/PKG-INFO
taicalculator.egg-info/SOURCES.txt
taicalculator.egg-info/dependency_links.txt
taicalculator.egg-info/top_level.txt